{
    "Name": "Inquiry-About-Fees-PostCall",
    "TriggerEventSource": {
        "EventSourceName": "OnPostCallAnalysisAvailable"
    },
    "Function": "{\"Version\":\"2022-11-25\",\"RuleFunction\":{\"Operator\":\"OR\",\"Operands\":[{\"Operator\":\"CONTAINS_ANY\",\"Operands\":[[{\"Type\":\"LIST\",\"Value\":[{\"Type\":\"PLAIN\",\"Value\":\"fee\"},{\"Type\":\"PLAIN\",\"Value\":\"charge\"},{\"Type\":\"PLAIN\",\"Value\":\"cost\"},{\"Type\":\"PLAIN\",\"Value\":\"expense\"},{\"Type\":\"PLAIN\",\"Value\":\"price\"},{\"Type\":\"PLAIN\",\"Value\":\"rate\"}]},{\"Type\":\"PLAIN\",\"Value\":\" \"},{\"Type\":\"PROXIMITY\",\"Value\":{\"Distance\":5,\"IsWithin\":true}},{\"Type\":\"PLAIN\",\"Value\":\" \"},{\"Type\":\"LIST\",\"Value\":[{\"Type\":\"PLAIN\",\"Value\":\"service\"},{\"Type\":\"PLAIN\",\"Value\":\"account\"},{\"Type\":\"PLAIN\",\"Value\":\"subscription\"},{\"Type\":\"PLAIN\",\"Value\":\"transaction\"},{\"Type\":\"PLAIN\",\"Value\":\"transfer\"}]}]],\"ComparisonValue\":\"$.ContactLens.PostCall.PatternMatch.Transcript\",\"FilterClause\":{\"LogicOperator\":\"AND\",\"Filters\":[{\"Type\":\"ParticipantRole\",\"Data\":\"CUSTOMER\"},{\"Type\":\"PatternMatchLanguageFilter\",\"Data\":\"EN\"}]},\"Negate\":false},{\"Operator\":\"CONTAINS_ANY\",\"Operands\":[\"What are the fees for my account?\",\"Can you explain the charges on my account?\",\"What's the cost of my subscription?\",\"Could you help me understand these expenses?\",\"What's the price for this service?\",\"Why is the rate so high?\",\"What fees am I being charged?\",\"Are there any hidden charges?\",\"Why is my account cost so high?\",\"Can you break down these expenses for me?\",\"How much does this service price?\",\"What's the current rate for this service?\",\"Why are these fees on my account?\",\"Can you clarify these charges for me?\",\"What does this cost cover?\",\"Why are there extra expenses?\",\"Can you explain the price for this service?\",\"Why did the rate increase?\",\"What additional fees should I expect?\",\"Are these charges correct?\",\"What is the total cost of my subscription?\",\"Why am I being charged these expenses?\",\"What's included in the service price?\",\"Has the rate for this service changed?\",\"Why are there unexpected fees on my account?\",\"Can you provide more details about these charges?\",\"Can you clarify why the cost is so high?\",\"Are there any expenses I'm not aware of?\",\"Why is the service price so high?\",\"What's the basis for these rates?\",\"How are these fees calculated?\",\"Why am I being charged for this service?\",\"Are these costs annual or monthly?\",\"Can you give me a breakdown of these charges?\",\"What will be my monthly cost?\",\"Why am I being charged extra?\",\"Can you explain the additional costs?\",\"Why are these fees appearing now?\",\"Are there any other charges I should be aware of?\",\"What's the cost of upgrading my account?\",\"Can you explain the rate increase?\"],\"ComparisonValue\":\"$.ContactLens.PostCall.ExactMatch.Transcript\",\"FilterClause\":{\"LogicOperator\":\"AND\",\"Filters\":[{\"Type\":\"ParticipantRole\",\"Data\":\"CUSTOMER\"}]},\"Negate\":false}]}}",
    "Actions": [
        {
            "ActionType": "ASSIGN_CONTACT_CATEGORY",
            "AssignContactCategoryAction": {}
        }
    ],
    "PublishStatus": "PUBLISHED"
}
